[[0.09363200000000001,{"lines":{"0":[["                                                                                                                                                                                                                                               ",{}]],"1":[["                                                                                                                                                                                                                                               ",{}]],"2":[["                                                                                                                                                                                                                                               ",{}]],"3":[["                                                                                                                                                                                                                                               ",{}]],"4":[["                                                                                                                                                                                                                                               ",{}]],"5":[["                                                                                                                                                                                                                                               ",{}]],"6":[["                                                                                                                                                                                                                                               ",{}]],"7":[["                                                                                                                                                                                                                                               ",{}]],"8":[["                                                                                                                                                                                                                                               ",{}]],"9":[["                                                                                                                                                                                                                                               ",{}]],"10":[["                                                                                                                                                                                                                                               ",{}]],"11":[["                                                                                                                                                                                                                                               ",{}]],"12":[["                                                                                                                                                                                                                                               ",{}]],"13":[["                                                                                                                                                                                                                                               ",{}]],"14":[["                                                                                                                                                                                                                                               ",{}]],"15":[["                                                                                                                                                                                                                                               ",{}]],"16":[["                                                                                                                                                                                                                                               ",{}]],"17":[["                                                                                                                                                                                                                                               ",{}]]},"cursor":{"x":0,"y":0,"visible":true}}],[0.006858,{"lines":{"0":[["➜  ",{"fg":2,"bold":true}],["amAgent2 ",{"fg":6,"bold":true}],[" ",{"fg":4,"bold":true}],["                                                                                                                                                                                                                                  ",{}]]},"cursor":{"x":13}}],[1.528123,{"lines":{"0":[["➜  ",{"fg":2,"bold":true}],["amAgent2 ",{"fg":6,"bold":true}],[" ",{"fg":4,"bold":true}],["c                                                                                                                                                                                                                                 ",{}]]},"cursor":{"x":14}}],[0.136975,{"lines":{"0":[["➜  ",{"fg":2,"bold":true}],["amAgent2 ",{"fg":6,"bold":true}],[" ",{"fg":4,"bold":true}],["ca                                                                                                                                                                                                                                ",{}]]},"cursor":{"x":15}}],[0.103604,{"lines":{"0":[["➜  ",{"fg":2,"bold":true}],["amAgent2 ",{"fg":6,"bold":true}],[" ",{"fg":4,"bold":true}],["cal                                                                                                                                                                                                                               ",{}]]},"cursor":{"x":16}}],[0.180706,{}],[0.012453,{"lines":{"1":[["   Augusztus 2014                                                                                                                                                                                                                              ",{}]],"2":[[" v  h  k sz cs  p sz                                                                                                                                                                                                                           ",{}]],"3":[["                1  2                                                                                                                                                                                                                           ",{}]],"4":[[" 3  4  5  6  7 ",{}],[" 8",{"inverse":true}],["  9                                                                                                                                                                                                                           ",{}]],"5":[["10 11 12 13 14 15 16                                                                                                                                                                                                                           ",{}]],"6":[["17 18 19 20 21 22 23                                                                                                                                                                                                                           ",{}]],"7":[["24 25 26 27 28 29 30                                                                                                                                                                                                                           ",{}]],"8":[["31                                                                                                                                                                                                                                             ",{}]],"9":[["➜  ",{"fg":2,"bold":true}],["amAgent2 ",{"fg":6,"bold":true}],[" ",{"fg":4,"bold":true}],["                                                                                                                                                                                                                                  ",{}]]},"cursor":{"x":13,"y":9}}],[1.377927,{"cursor":{"x":0,"y":10}}]]